whoisfreaks/__init__.py
whoisfreaks/client.py
whoisfreaks/core/__init__.py
whoisfreaks/core/api_error.py
whoisfreaks/core/client_wrapper.py
whoisfreaks/core/datetime_utils.py
whoisfreaks/core/file.py
whoisfreaks/core/http_client.py
whoisfreaks/core/http_response.py
whoisfreaks/core/jsonable_encoder.py
whoisfreaks/core/pydantic_utilities.py
whoisfreaks/core/query_encoder.py
whoisfreaks/core/remove_none_from_dict.py
whoisfreaks/core/request_options.py
whoisfreaks/core/serialization.py
whoisfreaks/credits/__init__.py
whoisfreaks/credits/client.py
whoisfreaks/credits/raw_client.py
whoisfreaks/credits/types/__init__.py
whoisfreaks/credits/types/api_credits.py
whoisfreaks/credits/types/api_subscription.py
whoisfreaks/credits/types/credits_response.py
whoisfreaks/dns/__init__.py
whoisfreaks/dns/client.py
whoisfreaks/dns/raw_client.py
whoisfreaks/dns/types/__init__.py
whoisfreaks/dns/types/bulk_dns_info.py
whoisfreaks/dns/types/bulk_dns_response.py
whoisfreaks/dns/types/dns_historical_response.py
whoisfreaks/dns/types/dns_live_response.py
whoisfreaks/dns/types/dns_record.py
whoisfreaks/dns/types/dns_reverse_response.py
whoisfreaks/dns/types/historical_dns_record.py
whoisfreaks/domain_availability/__init__.py
whoisfreaks/domain_availability/client.py
whoisfreaks/domain_availability/raw_client.py
whoisfreaks/domain_availability/types/__init__.py
whoisfreaks/domain_availability/types/bulk_domain_availability.py
whoisfreaks/domain_availability/types/bulk_domain_availability_response.py
whoisfreaks/domain_availability/types/domain_availability.py
whoisfreaks/domain_availability/types/domain_availability_response.py
whoisfreaks/environment.py
whoisfreaks/py.typed
whoisfreaks/ssl/__init__.py
whoisfreaks/ssl/client.py
whoisfreaks/ssl/raw_client.py
whoisfreaks/ssl/types/__init__.py
whoisfreaks/ssl/types/authority_info_access.py
whoisfreaks/ssl/types/certificate_policy.py
whoisfreaks/ssl/types/ssl_certificate.py
whoisfreaks/ssl/types/ssl_extensions.py
whois_sdk-1.0.23.dist-info/METADATA
whois_sdk-1.0.23.dist-info/WHEEL
whois_sdk-1.0.23.dist-info/RECORD
